fenrirWeb/__init__.py
fenrirWeb/lib.py
fenrirWeb/main.py
fenrirWeb/view_config.py
fenrirWeb/view_main.py
fenrirWeb/static/bootstrap.bundle.min.js
fenrirWeb/static/bootstrap.min.css
fenrirWeb/static/bootstrap.min.js
fenrirWeb/static/disabled.png
fenrirWeb/static/disabled.svg
fenrirWeb/static/enabled.png
fenrirWeb/static/enabled.svg
fenrirWeb/static/favicon.ico
fenrirWeb/static/fenrir.js
fenrirWeb/static/settings.png
fenrirWeb/views/changepassword.tpl
fenrirWeb/views/createpassword.tpl
fenrirWeb/views/index.tpl
fenrirWeb/views/mappinginput.tpl
fenrirWeb/views/navbar.tpl
fenrirWeb/views/settings.tpl
fenrirWeb/views/vpninput.tpl
fenrirWeb-0.6.0.dist-info/LICENSE
fenrirWeb-0.6.0.dist-info/METADATA
fenrirWeb-0.6.0.dist-info/WHEEL
fenrirWeb-0.6.0.dist-info/entry_points.txt
fenrirWeb-0.6.0.dist-info/top_level.txt
fenrirWeb-0.6.0.dist-info/RECORD
