Metadata-Version: 2.1
Name: fenrirWeb
Version: 0.6.0
Summary: use FenrirWeb as WebInterface for fenrir in order to show and configure VPN route enforcement
License-File: LICENSE
Requires-Dist: Bottle
Requires-Dist: jinja2
Requires-Dist: bcrypt
Requires-Dist: fenrircore
